setup.cfg
setup.py
tobd_ex/tobd_ex.py
tobd_ex.egg-info/PKG-INFO
tobd_ex.egg-info/SOURCES.txt
tobd_ex.egg-info/dependency_links.txt
tobd_ex.egg-info/not-zip-safe
tobd_ex.egg-info/top_level.txt