Metadata-Version: 2.1
Name: tobd-ex
Version: 0.0
Summary: tobd_ex
Author-email: ilapronin0700@gmail.com
